htmlflow/__init__.py
htmlflow-0.0.0.dist-info/METADATA
htmlflow-0.0.0.dist-info/WHEEL
htmlflow-0.0.0.dist-info/top_level.txt
htmlflow-0.0.0.dist-info/RECORD
