Metadata-Version: 2.1
Name: htmlflow
Version: 0.0.0
Summary: Coming soon
Author-email: Josh Tanke <josh@launchflow.com>
